propythia/__init__.py
propythia/clustering.py
propythia/feature_selection.py
propythia/linear_dim_reduction.py
propythia/manifold.py
propythia/preprocess.py
propythia/dna/__init__.py
propythia/dna/calculate_features.py
propythia/dna/descriptors.py
propythia/dna/encoding.py
propythia/dna/sequence.py
propythia/dna/utils.py
propythia/dna/data/mmc3.data
propythia/dna/data/mmc4.data
propythia/ml/__init__.py
propythia/ml/attention.py
propythia/ml/deep_ml.py
propythia/ml/param_optimizer.py
propythia/ml/parameters_deep.py
propythia/ml/parameters_shallow.py
propythia/ml/plot_curves_ml_propythia.py
propythia/ml/shallow_ml.py
propythia/ml/utils.py
propythia/ml/dl_basic_models/__init__.py
propythia/ml/dl_basic_models/basic_models_autoencoders.py
propythia/ml/dl_basic_models/basic_models_cnn.py
propythia/ml/dl_basic_models/basic_models_dnn.py
propythia/ml/dl_basic_models/basic_models_hybrid.py
propythia/ml/dl_basic_models/basic_models_lstm.py
propythia/ml/scoring/__init__.py
propythia/ml/scoring/scores.py
propythia/ml/torch/__init__.py
propythia/ml/torch/config.json
propythia/ml/torch/deep_ml.py
propythia/ml/torch/hyperparameter_tuning.py
propythia/ml/torch/models.py
propythia/ml/torch/prepare_data.py
propythia/ml/torch/test.py
propythia/ml/torch/train.py
propythia/ml/torch/utils.py
propythia/protein/__init__.py
propythia/protein/descriptors.py
propythia/protein/encoding.py
propythia/protein/protein_sequence.py
propythia/protein/sequence.py
propythia/protein/adjuv_functions/__init__.py
propythia/protein/adjuv_functions/data/PhysicoChemical.csv
propythia/protein/adjuv_functions/data/aaindex1
propythia/protein/adjuv_functions/data/aaindex2
propythia/protein/adjuv_functions/data/aaindex3
propythia/protein/adjuv_functions/data/blosum50.csv
propythia/protein/adjuv_functions/data/blosum62.csv
propythia/protein/adjuv_functions/data/bonds.csv
propythia/protein/adjuv_functions/data/nlf.csv
propythia/protein/adjuv_functions/features_functions/__init__.py
propythia-3.0.2.dist-info/METADATA
propythia-3.0.2.dist-info/WHEEL
propythia-3.0.2.dist-info/licenses/LICENSE
propythia-3.0.2.dist-info/RECORD
