Metadata-Version: 2.1
Name: propythia
Version: 3.0.2
Summary: Propythia - A platform for classification of peptides/proteins using machine and deep learning
Project-URL: Homepage, https://github.com/BioSystemsUM/propythia
Project-URL: Bug Tracker, https://github.com/BioSystemsUM/propythia/issues
Author: Contributors: Miguel Barros, Contributors: João Abreu, Contributors: Ivan Gomes
Author-email: "Main Author: Ana Marta Sequeira" <id9417@alunos.uminho.pt>
License: GNU GENERAL PUBLIC LICENSE
License-File: LICENSE
Classifier: Operating System :: OS Independent
Classifier: Programming Language :: Python :: 3
Requires-Python: >=3.7
